jsonkeysearch/__init__.py
jsonkeysearch/jsonkeysearch.py
jsonkeysearch/sample.py
jsonkeysearch-0.1.1.dist-info/LICENSE
jsonkeysearch-0.1.1.dist-info/METADATA
jsonkeysearch-0.1.1.dist-info/WHEEL
jsonkeysearch-0.1.1.dist-info/top_level.txt
jsonkeysearch-0.1.1.dist-info/RECORD
