Metadata-Version: 2.1
Name: jsonkeysearch
Version: 0.1.1
Summary: jsonkeysearch: Searches for keys in JSON format files.
Home-page: https://github.com/gmoriki/jsonkeysearch
Download-URL: https://github.com/gmoriki/jsonkeysearch
Author: MORIKI Ginga
Author-email: gingiragin@outlook.jp
Maintainer: MORIKI Ginga
Maintainer-email: gingiragin@outlook.jp
License: MIT
Keywords: json search
Classifier: License :: OSI Approved :: MIT License
Classifier: Programming Language :: Python :: 3.10
License-File: LICENSE
